mindustry.py
mindustry-1.3.8.dist-info/WHEEL
mindustry-1.3.8.dist-info/METADATA
mindustry-1.3.8.dist-info/RECORD
